parityvend_api/__init__.py
parityvend_api/config.py
parityvend_api/data.py
parityvend_api/exceptions.py
parityvend_api/handler.py
parityvend_api/handler_async.py
parityvend_api/objects.py
parityvend_api/utils.py
parityvend_api/cache/__init__.py
parityvend_api/cache/default.py
parityvend_api/cache/interface.py
parityvend_api-1.0.1.dist-info/LICENSE
parityvend_api-1.0.1.dist-info/METADATA
parityvend_api-1.0.1.dist-info/WHEEL
parityvend_api-1.0.1.dist-info/top_level.txt
parityvend_api-1.0.1.dist-info/RECORD
