Metadata-Version: 2.1
Name: parityvend_api
Version: 1.0.1
Summary: The official Python library for ParityVend API
Home-page: https://github.com/parityvend/api_python
Author: ParityVend
Author-email: ParityVend <help@ambeteco.com>
License: Apache-2.0
Project-URL: Homepage, https://github.com/ParityVend/parityvend_api_python/
Project-URL: Repository, https://github.com/ParityVend/parityvend_api_python/
Project-URL: Documentation, https://www.ambeteco.com/ParityVend/docs/index.html
Project-URL: Changelog, https://raw.githubusercontent.com/ParityVend/parityvend_api_python/main/CHANGELOG.MD
Keywords: parityvend,purchasing power parity,purchasing power,location based pricing,pricing optimization,api library,geographical pricing,dynamic pricing
Classifier: Development Status :: 5 - Production/Stable
Classifier: Typing :: Typed
Classifier: Intended Audience :: Developers
Classifier: Programming Language :: Python
Classifier: Programming Language :: Python :: 3
Classifier: Programming Language :: Python :: 3 :: Only
Classifier: Programming Language :: Python :: 3.8
Classifier: Programming Language :: Python :: 3.9
Classifier: Programming Language :: Python :: 3.10
Classifier: Programming Language :: Python :: 3.11
Classifier: Programming Language :: Python :: 3.12
Classifier: Programming Language :: Python :: 3.13
Classifier: Programming Language :: Python :: Implementation :: CPython
Classifier: Programming Language :: Python :: Implementation :: PyPy
Classifier: Operating System :: OS Independent
Classifier: Framework :: AsyncIO
Classifier: Framework :: Pytest
Classifier: Framework :: aiohttp
Classifier: Topic :: Internet
Classifier: Topic :: Internet :: WWW/HTTP
Classifier: Topic :: Software Development :: Libraries
Classifier: Topic :: Software Development :: Libraries :: Python Modules
Classifier: Topic :: Utilities
Classifier: Topic :: Office/Business :: Financial
Classifier: License :: OSI Approved :: Apache Software License
Requires-Python: >=3.8
License-File: LICENSE
Requires-Dist: requests>=2.31.0
Requires-Dist: cachetools>=5.3.3
Requires-Dist: aiohttp>=3.9.3
